difi/__init__.py
difi/cifi.py
difi/difi.py
difi/io.py
difi/metrics.py
difi/utils.py
difi/version.py
difi-1.1.dist-info/LICENSE.md
difi-1.1.dist-info/METADATA
difi-1.1.dist-info/WHEEL
difi-1.1.dist-info/top_level.txt
difi-1.1.dist-info/RECORD
