Metadata-Version: 2.1
Name: difi
Version: 1.1
Summary: Did I Find It?
Home-page: https://github.com/moeyensj/difi
Author: Joachim Moeyens
Author-email: moeyensj@uw.edu
License: BSD 3-Clause License
Keywords: astronomy,astrophysics,space,science,asteroids,comets,solar system
Platform: UNKNOWN
Classifier: Development Status :: 3 - Alpha
Classifier: Intended Audience :: Science/Research
Classifier: License :: OSI Approved :: BSD License
Classifier: Operating System :: OS Independent
Classifier: Programming Language :: Python
Classifier: Programming Language :: Python :: 3.7
Classifier: Programming Language :: Python :: 3.8
Classifier: Topic :: Scientific/Engineering :: Astronomy
Classifier: Topic :: Scientific/Engineering :: Physics
Requires-Python: >=3.7
Requires-Dist: numpy
Requires-Dist: pandas
